pylsp_ruff_signature/__init__.py
pylsp_ruff_signature-0.1.0.dist-info/METADATA
pylsp_ruff_signature-0.1.0.dist-info/WHEEL
pylsp_ruff_signature-0.1.0.dist-info/entry_points.txt
pylsp_ruff_signature-0.1.0.dist-info/licenses/LICENSE
pylsp_ruff_signature-0.1.0.dist-info/RECORD
